{
  "bomFormat": "CycloneDX",
  "specVersion": "1.5",
  "metadata": {
    "component": {
      "purl": "3",
      "bom-ref": "3"
    }
  },
  "components": [
    {
      "purl": "1",
      "type": "application",
      "bom-ref": "1"
    },
    {
      "purl": "2",
      "type": "application",
      "bom-ref": "2"
    },
    {
      "purl": "B",
      "type": "application",
      "bom-ref": "B"
    },
    {
      "purl": "D",
      "type": "application",
      "bom-ref": "D"
    }
  ],
  "dependencies": [
    {
      "ref": "3",
      "dependsOn": ["1", "2"]
    },
    {
      "ref": "2",
      "dependsOn": ["B"]
    },
    {
      "ref": "D",
      "dependsOn": ["B"]
    }
  ]
}